Workbook

Sheet تعليمات
A1: مجموعة الاختبار — testset
A3: ■ الغرض
A4: هذه المجموعة هي الدليل الذي تقدّمه للجنة: يشغّل سكربت القياس المدقّق عليها ويحسب الدقة ونسبة الامتناع الصحيح. جودتها تساوي مصداقية أرقامك.
A6: ■ الحجم: 200 حالة موزعة على 9 فئات (انظر ورقة «التقدّم» لترى ما أنجزت من كل فئة).
A8: ■ طريقة التعبئة
A9: 1) النص: فقرة واقعية كاملة (من منشور أو مخطوطة أو ترجمة)، تحوي استشهادًا واحدًا رئيسيًا. لا تكتب جملة معزولة.
A10: 2) الفئة واللغة والنوع والحالة المتوقعة: من القوائم المنسدلة.
A11: 3) المرجع المتوقع: للآيات «رقم السورة:رقم الآية» مثل 51:56، وللأحاديث معرّف الحديث في الفهرس مثل h-012. اتركه فارغًا للفئتين C8 وC9.
A12: 4) الحالة المتوقعة للأحاديث تُؤخذ من أحكام الفهرس: إن اختلفت أحكام المحدّثين فاكتب HADITH_MULTIPLE_RULINGS.
A13: 5) المراجعة: يراجع المراجع الشرعي كل حالة ويختار «مقبول» أو «يحتاج تعديل». لا تُحتسب في القياس إلا الحالات المقبولة.
A15: ■ التقسيم (split)
A16: المعرّفات المجهّزة مقسّمة مسبقًا: كل رابع حالة dev (50 حالة لضبط المدقّق)، والباقي test (150 حالة للقياس النهائي فقط). وزّع الفئات على الصفوف بحيث يكون في dev نحو ربع كل فئة؛ ورقة «التقدّم» تريك ذلك.
... A22: ■ الصفوف الرمادية أمثلة (المعرّف EX) ويتجاهلها السكربت.

Sheet الحالات
A1: المعرّف * | B1: التقسيم * | C1: الفئة * | D1: اللغة * | E1: النوع * | F1: الوحدة * | G1: النص (فقرة واقعية) * | H1: الحالة المتوقعة * | I1: المرجع المتوقع | J1: مصدر النص | K1: المراجع | L1: نتيجة المراجعة * | M1: ملاحظات
A2: id | B2: split | C2: category | D2: lang | E2: kind | F2: target_module | G2: text | H2: expected_status | I2: expected_ref | J2: text_origin | K2: reviewed_by | L2: review_status | M2: notes
A3: EX-1 | B3: dev | C3: C1 آيات عربية صحيحة | D3: ar | E3: quran | F3: verifier | G3: غاية وجود الإنسان في الإسلام واضحة، قال تعالى: ﴿وَمَا خَلَقْتُ الْجِنَّ وَالْإِنسَ إِلَّا لِيَعْبُدُونِ﴾، فالعبادة بمعناها الشامل هي مقصد الخلق. | H3: QURAN_VERIFIED | I3: 51:56 | J3: مثال | L3: مقبول
A4: EX-2 | B4: dev | C4: C2 آيات محرفة اللفظ | D4: ar | E4: quran | F4: verifier | G4: وقد بيّن القرآن الغاية من الخلق بقوله: «وما خلقنا الجن والإنس إلا ليعبدون». | H4: QURAN_WORDING_DIFFERS | I4: 51:56 | J4: مثال | L4: مقبول | M4: «خلقنا» بدل «خلقتُ»
A5: t-001 | B5: test | C5: C1 آيات عربية صحيحة | D5: ar | E5: quran | F5: verifier | G5: من أعظم ما يطمئن به القلب أن الله تعالى قال في كتابه: ﴿رَبَّنَا لَا تُزِغْ قُلُوبَنَا بَعْدَ إِذْ هَدَيْتَنَا وَهَبْ لَنَا مِنْ لَدُنْكَ رَحْمَةً إِنَّكَ أَنْتَ الْوَهَّابُ﴾، فهذه الآية تفتح باب الأمل لكل من ضاقت به الدنيا. | H5: QURAN_VERIFIED | I5: 3:8 | J5: نص الآية من فهرس المصحف في المكتبة الشاملة (إملائي) | K5: محمد سجاد | L5: مقبول
A6: t-002 | B6: test | C6: C1 آيات عربية صحيحة | D6: ar | E6: quran | F6: verifier | G6: يقول الله عز وجل: فبما رحمة من الله لنت لهم ولو كنت فظا غليظ القلب لانفضوا من حولك فاعف عنهم واستغفر لهم وشاورهم في الأمر فإذا عزمت فتوكل على الله إن الله يحب المتوكلين. وفي هذا تذكير لنا بأن الرحمة أصل في تعامل المسلم مع الناس. | H6: QURAN_VERIFIED | I6: 3:159 | J6: نص الآية من فهرس المصحف في المكتبة الشاملة (إملائي)، بلا تشكيل | K6: محمد سجاد | L6: مقبول
A7: t-003 | B7: test | C7: C1 آيات عربية صحيحة | D7: ar | E7: quran | F7: verifier | G7: أخي الكريم، تأمل قوله تعالى: «فَأَمَّا الَّذِينَ آمَنُوا بِاللَّهِ وَاعْتَصَمُوا بِهِ فَسَيُدْخِلُهُمْ فِي رَحْمَةٍ مِنْهُ وَفَضْلٍ وَيَهْدِيهِمْ إِلَيْهِ صِرَاطًا مُسْتَقِيمًا»، ثم انظر كيف ينبغي أن يكون حالنا مع إخواننا في هذا المجتمع. | H7: QURAN_VERIFIED | I7: 4:175 | J7: نص الآية من فهرس المصحف في المكتبة الشاملة (إملائي) | K7: محمد سجاد | L7: مقبول
A8: t-004 | B8: dev | C8: C1 آيات عربية صحيحة | D8: ar | E8: quran | F8: verifier | G8: في درس الأمس بالمركز تحدثنا عن قول الله سبحانه: ﴿فإن كذبوك فقل ربكم ذو رحمة واسعة ولا يرد بأسه عن القوم المجرمين﴾، وكيف نشرح معناها لمن لا يعرف العربية. | H8: QURAN_VERIFIED | I8: 6:147 | J8: نص الآية من فهرس المصحف في المكتبة الشاملة (إملائي)، بلا تشكيل | K8: محمد سجاد | L8: مقبول
A9: t-005 | B9: test | C9: C1 آيات عربية صحيحة | D9: ar | E9: quran | F9: verifier | G9: قال الله تعالى: قَالَ وَمَنْ يَقْنَطُ مِنْ رَحْمَةِ رَبِّهِ إِلَّا الضَّالُّونَ صدق الله العظيم. | H9: QURAN_VERIFIED | I9: 15:56 | J9: نص الآية من فهرس المصحف في المكتبة الشاملة (إملائي) | K9: محمد سجاد | L9: مقبول
A10: t-006 | B10: test | C10: C1 آيات عربية صحيحة | D10: ar | E10: quran | F10: verifier | G10: منشور اليوم: ﴿وإما تعرضن عنهم ابتغاء رحمة من ربك ترجوها فقل لهم قولا ميسورا﴾ — شاركها مع من تحب ولا تنس الدعاء لنا. | H10: QURAN_VERIFIED | I10: 17:28 | J10: نص الآية من فهرس المصحف في المكتبة الشاملة (إملائي)، بلا تشكيل | K10: محمد سجاد | L10: مقبول
A11: t-007 | B11: test | C11: C1 آيات عربية صحيحة | D11: ar | E11: quran | F11: verifier | G11: ومن الأدلة على ذلك قوله تعالى: إِذْ أَوَى الْفِتْيَةُ إِلَى الْكَهْفِ فَقَالُوا رَبَّنَا آتِنَا مِنْ لَدُنْكَ رَحْمَةً وَهَيِّئْ لَنَا مِنْ أَمْرِنَا رَشَدًا، وهي آية جامعة يحسن بالداعية أن يحفظها. | H11: QURAN_VERIFIED | I11: 18:10 | J11: نص الآية من فهرس المصحف في المكتبة الشاملة (إملائي) | L11: لم يراجع
A12: t-008 | B12: dev | C12: C1 آيات عربية صحيحة | D12: ar | E12: quran | F12: verifier | G12: من أعظم ما يطمئن به القلب أن الله تعالى قال في كتابه: ﴿وما أرسلناك إلا رحمة للعالمين﴾، فهذه الآية تفتح باب الأمل لكل من ضاقت به الدنيا. | H12: QURAN_VERIFIED | I12: 21:107 | J12: نص الآية من فهرس المصحف في المكتبة الشاملة (إملائي)، بلا تشكيل | L12: مقبول
A13: t-009 | B13: test | C13: C1 آيات عربية صحيحة | D13: ar | E13: quran | F13: verifier | G13: يقول الله عز وجل: مَا يَفْتَحِ اللَّهُ لِلنَّاسِ مِنْ رَحْمَةٍ فَلَا مُمْسِكَ لَهَا وَمَا يُمْسِكْ فَلَا مُرْسِلَ لَهُ مِنْ بَعْدِهِ وَهُوَ الْعَزِيزُ الْحَكِيمُ. وفي هذا تذكير لنا بأن الرحمة أصل في تعامل المسلم مع الناس. | H13: QURAN_VERIFIED | I13: 35:2 | J13: نص الآية من فهرس المصحف في المكتبة الشاملة (إملائي) | L13: لم يراجع
A14: t-010 | B14: test | C14: C1 آيات عربية صحيحة | D14: ar | E14: quran | F14: verifier | G14: أخي الكريم، تأمل قوله تعالى: «أمن هو قانت آناء الليل ساجدا وقائما يحذر الآخرة ويرجو رحمة ربه قل هل يستوي الذين يعلمون والذين لا يعلمون إنما يتذكر أولو الألباب»، ثم انظر كيف ينبغي أن يكون حالنا مع إخواننا في هذا المجتمع. | H14: QURAN_VERIFIED | I14: 39:9 | J14: نص الآية من فهرس المصحف في المكتبة الشاملة (إملائي)، بلا تشكيل | L14: لم يراجع
A15: t-011 | B15: test | C15: C1 آيات عربية صحيحة | D15: ar | E15: quran | F15: verifier | G15: في درس الأمس بالمركز تحدثنا عن قول الله سبحانه: ﴿قُلْ يَاعِبَادِيَ الَّذِينَ أَسْرَفُوا عَلَى أَنْفُسِهِمْ لَا تَقْنَطُوا مِنْ رَحْمَةِ اللَّهِ إِنَّ اللَّهَ يَغْفِرُ الذُّنُوبَ جَمِيعًا إِنَّهُ هُوَ الْغَفُورُ الرَّحِيمُ﴾، وكيف نشرح معناها لمن لا يعرف العربية. | H15: QURAN_VERIFIED | I15: 39:53 | J15: نص الآية من فهرس المصحف في المكتبة الشاملة (إملائي) | K15: محمد سجاد | L15: مقبول
A16: t-012 | B16: dev | C16: C1 آيات عربية صحيحة | D16: ar | E16: quran | F16: verifier | G16: قال الله تعالى: الذين يحملون العرش ومن حوله يسبحون بحمد ربهم ويؤمنون به ويستغفرون للذين آمنوا ربنا وسعت كل شيء رحمة وعلما فاغفر للذين تابوا واتبعوا سبيلك وقهم عذاب الجحيم صدق الله العظيم. | H16: QURAN_VERIFIED | I16: 40:7 | J16: نص الآية من فهرس المصحف في المكتبة الشاملة (إملائي)، بلا تشكيل | K16: محمد سجاد | L16: مقبول
A17: t-013 | B17: test | C17: C1 آيات عربية صحيحة | D17: ar | E17: quran | F17: verifier | G17: منشور اليوم: ﴿رَحْمَةً مِنْ رَبِّكَ إِنَّهُ هُوَ السَّمِيعُ الْعَلِيمُ﴾ — شاركها مع من تحب ولا تنس الدعاء لنا. | H17: QURAN_VERIFIED | I17: 44:6 | J17: نص الآية من فهرس المصحف في المكتبة الشاملة (إملائي) | L17: مقبول
A18: t-014 | B18: test | C18: C1 آيات عربية صحيحة | D18: ar | E18: quran | F18: verifier | G18: ومن الأدلة على ذلك قوله تعالى: وَإِذَا سَأَلَكَ عِبَادِي عَنِّي فَإِنِّي قَرِيبٌۖ أُجِيبُ دَعۡوَةَ ٱلدَّاعِ إِذَا دَعَانِۖ فَلۡيَسۡتَجِيبُواْ لِي وَلۡيُؤۡمِنُواْ بِي لَعَلَّهُمۡ يَرۡشُدُونَ، وهي آية جامعة يحسن بالداعية أن يحفظها. | H18: QURAN_VERIFIED | I18: 2:186 | J18: نص الآية بالرسم العثماني من QuranEnc عبر حزمة quran-json | L18: مقبول
A19: t-015 | B19: test | C19: C1 آيات عربية صحيحة | D19: ar | E19: quran | F19: verifier | G19: من أعظم ما يطمئن به القلب أن الله تعالى قال في كتابه: ﴿ٱلَّذِينَ ءَامَنُواْ وَتَطۡمَئِنُّ قُلُوبُهُم بِذِكۡرِ ٱللَّهِۗ أَلَا بِذِكۡرِ ٱللَّهِ تَطۡمَئِنُّ ٱلۡقُلُوبُ﴾، فهذه الآية تفتح باب الأمل لكل من ضاقت به الدنيا. | H19: QURAN_VERIFIED | I19: 13:28 | J19: نص الآية بالرسم العثماني من QuranEnc عبر حزمة quran-json | L19: مقبول
A20: t-016 | B20: dev | C20: C1 آيات عربية صحيحة | D20: ar | E20: quran | F20: verifier | G20: يقول الله عز وجل: يَـٰٓأَيُّهَا ٱلنَّاسُ إِنَّا خَلَقۡنَٰكُم مِّن ذَكَرٖ وَأُنثَىٰ وَجَعَلۡنَٰكُمۡ شُعُوبٗا وَقَبَآئِلَ لِتَعَارَفُوٓاْۚ إِنَّ أَكۡرَمَكُمۡ عِندَ ٱللَّهِ أَتۡقَىٰكُمۡۚ إِنَّ ٱللَّهَ عَلِيمٌ خَبِيرٞ. تبيّن الآية أن معيار الكرامة عند الله هو التقوى. | H20: QURAN_VERIFIED | I20: 49:13 | J20: نص الآية بالرسم العثماني من QuranEnc عبر حزمة quran-json | K20: محمد سجاد | L20: مقبول
A21: t-017 | B21: test | C21: C1 آيات عربية صحيحة | D21: ar | E21: quran | F21: verifier | G21: أخي الكريم، تأمل قوله تعالى: «ٱدۡعُ إِلَىٰ سَبِيلِ رَبِّكَ بِٱلۡحِكۡمَةِ وَٱلۡمَوۡعِظَةِ ٱلۡحَسَنَةِۖ وَجَٰدِلۡهُم بِٱلَّتِي هِيَ أَحۡسَنُۚ إِنَّ رَبَّكَ هُوَ أَعۡلَمُ بِمَن ضَلَّ عَن سَبِيلِهِۦ وَهُوَ أَعۡلَمُ بِٱلۡمُهۡتَدِينَ»، ثم انظر كيف ينبغي أن يكون حالنا مع إخواننا في هذا المجتمع. | H21: QURAN_VERIFIED | I21: 16:125 | J21: نص الآية بالرسم العثماني من QuranEnc عبر حزمة quran-json | K21: محمد سجاد | L21: مقبول
A22: t-018 | B22: test | C22: C1 آيات عربية صحيحة | D22: ar | E22: quran | F22: verifier | G22: في درس الأمس بالمركز تحدثنا عن قول الله سبحانه: ﴿لَآ إِكۡرَاهَ فِي ٱلدِّينِۖ قَد تَّبَيَّنَ ٱلرُّشۡدُ مِنَ ٱلۡغَيِّۚ فَمَن يَكۡفُرۡ بِٱلطَّـٰغُوتِ وَيُؤۡمِنۢ بِٱللَّهِ فَقَدِ ٱسۡتَمۡسَكَ بِٱلۡعُرۡوَةِ ٱلۡوُثۡقَىٰ لَا ٱنفِصَامَ لَهَاۗ وَٱللَّهُ سَمِيعٌ عَلِيمٌ﴾، وكيف نشرح معناها لمن لا يعرف العربية. | H22: QURAN_VERIFIED | I22: 2:256 | J22: نص الآية بالرسم العثماني من QuranEnc عبر حزمة quran-json | L22: لم يراجع
A23: t-019 | B23: test | C23: C1 آيات عربية صحيحة | D23: ar | E23: quran | F23: verifier | G23: قال الله تعالى: قُلۡ هُوَ ٱللَّهُ أَحَدٌ صدق الله العظيم. فلنجعل هذه الآية شعارنا في دعوتنا هذا الأسبوع. | H23: QURAN_VERIFIED | I23: 112:1 | J23: نص الآية بالرسم العثماني من QuranEnc عبر حزمة quran-json | L23: لم يراجع
A24: t-020 | B24: dev | C24: C1 آيات عربية صحيحة | D24: ar | E24: quran | F24: verifier | G24: منشور اليوم: ﴿كُلُّ نَفۡسٖ ذَآئِقَةُ ٱلۡمَوۡتِۗ وَإِنَّمَا تُوَفَّوۡنَ أُجُورَكُمۡ يَوۡمَ ٱلۡقِيَٰمَةِۖ فَمَن زُحۡزِحَ عَنِ ٱلنَّارِ وَأُدۡخِلَ ٱلۡجَنَّةَ فَقَدۡ فَازَۗ وَمَا ٱلۡحَيَوٰةُ ٱلدُّنۡيَآ إِلَّا مَتَٰعُ ٱلۡغُرُورِ﴾ — شاركها مع من تحب ولا تنس الدعاء لنا. | H24: QURAN_VERIFIED | I24: 3:185 | J24: نص الآية بالرسم العثماني من QuranEnc عبر حزمة quran-json | K24: محمد سجاد | L24: مقبول
A25: t-021 | B25: test | C25: C1 آيات عربية صحيحة | D25: ar | E25: quran | F25: verifier | G25: ومن الأدلة على ذلك قوله تعالى: لَّا يَنۡهَىٰكُمُ ٱللَّهُ عَنِ ٱلَّذِينَ لَمۡ يُقَٰتِلُوكُمۡ فِي ٱلدِّينِ وَلَمۡ يُخۡرِجُوكُم مِّن دِيَٰرِكُمۡ أَن تَبَرُّوهُمۡ وَتُقۡسِطُوٓاْ إِلَيۡهِمۡۚ إِنَّ ٱللَّهَ يُحِبُّ ٱلۡمُقۡسِطِينَ، وهي آية جامعة يحسن بالداعية أن يحفظها. | H25: QURAN_VERIFIED | I25: 60:8 | J25: نص الآية بالرسم العثماني من QuranEnc عبر حزمة quran-json | L25: لم يراجع
A26: t-022 | B26: test | C26: C1 آيات عربية صحيحة | D26: ar | E26: quran | F26: verifier | G26: من أعظم ما يطمئن به القلب أن الله تعالى قال في كتابه: ﴿وَٱلَّذِينَ جَٰهَدُواْ فِينَا لَنَهۡدِيَنَّهُمۡ سُبُلَنَاۚ وَإِنَّ ٱللَّهَ لَمَعَ ٱلۡمُحۡسِنِينَ﴾، فهذه الآية تفتح باب الأمل لكل من ضاقت به الدنيا. | H26: QURAN_VERIFIED | I26: 29:69 | J26: نص الآية بالرسم العثماني من QuranEnc عبر حزمة quran-json | L26: لم يراجع
A27: t-023 | B27: test | C27: C1 آيات عربية صحيحة | D27: ar | E27: quran | F27: verifier | G27: يقول الله عز وجل: يَـٰٓأَيُّهَا ٱلَّذِينَ ءَامَنُواْ كُتِبَ عَلَيۡكُمُ ٱلصِّيَامُ كَمَا كُتِبَ عَلَى ٱلَّذِينَ مِن قَبۡلِكُمۡ لَعَلَّكُمۡ تَتَّقُونَ. وفي هذه الآية دلالة على فرضية الصيام على المسلمين، وكما تدل على مقصد أكبر للصيام. | H27: QURAN_VERIFIED | I27: 2:183 | J27: نص الآية بالرسم العثماني من QuranEnc عبر حزمة quran-json | K27: محمد سجاد | L27: مقبول
A28: t-024 | B28: dev | C28: C1 آيات عربية صحيحة | D28: ar | E28: quran | F28: verifier | G28: أخي الكريم، تأمل قوله تعالى: «۞وَقَضَىٰ رَبُّكَ أَلَّا تَعۡبُدُوٓاْ إِلَّآ إِيَّاهُ وَبِٱلۡوَٰلِدَيۡنِ إِحۡسَٰنًاۚ إِمَّا يَبۡلُغَنَّ عِندَكَ ٱلۡكِبَرَ أَحَدُهُمَآ أَوۡ كِلَاهُمَا فَلَا تَقُل لَّهُمَآ أُفّٖ وَلَا تَنۡهَرۡهُمَا وَقُل لَّهُمَا قَوۡلٗا كَرِيمٗا»، ثم انظر كيف ينبغي أن يكون تعاملنا مع الوالدين. | H28: QURAN_VERIFIED | I28: 17:23 | J28: نص الآية بالرسم العثماني من QuranEnc عبر حزمة quran-json | K28: محمد سجاد | L28: مقبول
A29: t-025 | B29: test | C29: C1 آيات عربية صحيحة | D29: ar | E29: quran | F29: verifier | G29: في درس الأمس بالمركز تحدثنا عن قول الله سبحانه: ﴿يَـٰٓأَيُّهَا ٱلنَّاسُ ٱتَّقُواْ رَبَّكُمُ ٱلَّذِي خَلَقَكُم مِّن نَّفۡسٖ وَٰحِدَةٖ وَخَلَقَ مِنۡهَا زَوۡجَهَا وَبَثَّ مِنۡهُمَا رِجَالٗا كَثِيرٗا وَنِسَآءٗۚ وَٱتَّقُواْ ٱللَّهَ ٱلَّذِي تَسَآءَلُونَ بِهِۦ وَٱلۡأَرۡحَامَۚ إِنَّ ٱللَّهَ كَانَ عَلَيۡكُمۡ رَقِيبٗا﴾، وكيف نشرح معناها لمن لا يعرف العربية. | H29: QURAN_VERIFIED | I29: 4:1 | J29: نص الآية بالرسم العثماني من QuranEnc عبر حزمة quran-json | L29: لم يراجع
A30: t-026 | B30: test | C30: C2 آيات محرفة اللفظ | D30: ar | E30: quran | F30: verifier | G30: في درس الأمس بالمركز تحدثنا عن قول الله سبحانه: ﴿وَأَمَّا الَّذِينَ ابْيَضَّتْ وُجُوهُهُمْ فَفِي رَحْمَةِ اللَّهِ هُمْ فِيهَا مُخَلَّدُونَ﴾، وكيف نشرح معناها لمن لا يعرف العربية. | H30: QURAN_WORDING_DIFFERS | I30: 3:107 | J30: آية من فهرس المصحف في الشاملة غُيّرت فيها كلمة واحدة عمدًا | K30: محمد سجاد | L30: مقبول | M30: المحرّف: «مخلدون» بدل «خالدون»
A31: t-027 | B31: test | C31: C2 آيات محرفة اللفظ | D31: ar | E31: quran | F31: verifier | G31: قال الله تعالى: من يصرف عنه يومئذ فقد رحمه وذلك الفوز العظيم صدق الله العظيم. فلنجعل هذه الآية شعارنا في دعوتنا هذا الأسبوع. | H31: QURAN_WORDING_DIFFERS | I31: 6:16 | J31: آية من فهرس المصحف في الشاملة غُيّرت فيها كلمة واحدة عمدًا | L31: لم يراجع | M31: المحرّف: «العظيم» بدل «المبين»
A32: t-028 | B32: test | C32: C2 آيات محرفة اللفظ | D32: ar | E32: quran | F32: verifier | G32: منشور اليوم: ﴿وَلَئِنْ أَذَقْنَا الْإِنْسَانَ مِنَّا رَحْمَةً ثُمَّ نَزَعْنَاهَا مِنْهُ إِنَّهُ لَقَنُوطٌ كَفُورٌ﴾ — شاركها مع من تحب ولا تنس الدعاء لنا. | H32: QURAN_WORDING_DIFFERS | I32: 11:9 | J32: آية من فهرس المصحف في الشاملة غُيّرت فيها كلمة واحدة عمدًا | L32: لم يراجع | M32: المحرّف: «لقنوط» بدل «ليئوس»
A33: t-029 | B33: dev | C33: C2 آيات محرفة اللفظ | D33: ar | E33: quran | F33: verifier | G33: ومن الأدلة على ذلك قوله تعالى: إلا رحمة من ربك إن فضله كان عليك عظيما، وهي آية جامعة يحسن بالداعية أن يحفظها. | H33: QURAN_WORDING_DIFFERS | I33: 17:87 | J33: آية من فهرس المصحف في الشاملة غُيّرت فيها كلمة واحدة عمدًا | K33: محمد سجاد | L33: مقبول | M33: المحرّف: «عظيما» بدل «كبيرا»
A34: t-030 | B34: test | C34: C2 آيات محرفة اللفظ | D34: ar | E34: quran | F34: verifier | G34: من أعظم ما يطمئن به القلب أن الله تعالى قال في كتابه: ﴿قُلْ لَوْ أَنْتُمْ تَمْلِكُونَ خَزَائِنَ رَحْمَةِ رَبِّي إِذًا لَأَمْسَكْتُمْ خَشْيَةَ الْإِنْفَاقِ وَكَانَ الْإِنْسَانُ كَفُورًا﴾، فهذه الآية تفتح باب الأمل لكل من ضاقت به الدنيا. | H34: QURAN_WORDING_DIFFERS | I34: 17:100 | J34: آية من فهرس المصحف في الشاملة غُيّرت فيها كلمة واحدة عمدًا | K34: محمد سجاد | L34: مقبول | M34: المحرّف: «كفورا» بدل «قتورا»
A35: t-031 | B35: test | C35: C2 آيات محرفة اللفظ | D35: ar | E35: quran | F35: verifier | G35: يقول الله عز وجل: فوجدا عبدا من عبادنا آتيناه رحمة من عندنا وعلمناه من عندنا علما. وفي هذا تذكير لنا بأن الرحمة أصل في تعامل المسلم مع الناس. | H35: QURAN_WORDING_DIFFERS | I35: 18:65 | J35: آية من فهرس المصحف في الشاملة غُيّرت فيها كلمة واحدة عمدًا | L35: لم يراجع | M35: المحرّف: «من عندنا» بدل «من لدنا»
A36: t-032 | B36: test | C36: C2 آيات محرفة اللفظ | D36: ar | E36: quran | F36: verifier | G36: أخي الكريم، تأمل قوله تعالى: «قَالَ هَذَا رَحْمَةٌ مِنْ رَبِّي فَإِذَا جَاءَ وَعْدُ رَبِّي جَعَلَهُ دَكًّا وَكَانَ وَعْدُ رَبِّي حَقًّا»، ثم انظر كيف ينبغي أن يكون حالنا مع إخواننا في هذا المجتمع. | H36: QURAN_WORDING_DIFFERS | I36: 18:98 | J36: آية من فهرس المصحف في الشاملة غُيّرت فيها كلمة واحدة عمدًا | L36: لم يراجع | M36: المحرّف: «دكا» بدل «دكاء»
A37: t-033 | B37: dev | C37: C2 آيات محرفة اللفظ | D37: ar | E37: quran | F37: verifier | G37: في درس الأمس بالمركز تحدثنا عن قول الله سبحانه: ﴿فاستجبنا له فكشفنا ما به من ضر وآتيناه أهله ومثلهم معهم رحمة من عندنا وذكرى للمؤمنين﴾، وكيف نشرح معناها لمن لا يعرف العربية. | H37: QURAN_WORDING_DIFFERS | I37: 21:84 | J37: آية من فهرس المصحف في الشاملة غُيّرت فيها كلمة واحدة عمدًا | K37: محمد سجاد | L37: مقبول | M37: المحرّف: «للمؤمنين» بدل «للعابدين»
A38: t-034 | B38: test | C38: C2 آيات محرفة اللفظ | D38: ar | E38: quran | F38: verifier | G38: قال الله تعالى: وَمَا كُنْتَ تَرْجُو أَنْ يُلْقَى إِلَيْكَ الْكِتَابُ إِلَّا رَحْمَةً مِنْ رَبِّكَ فَلَا تَكُونَنَّ نَصِيرًا لِلْكَافِرِينَ صدق الله العظيم. فلنجعل هذه الآية شعارنا في دعوتنا هذا الأسبوع. | H38: QURAN_WORDING_DIFFERS | I38: 28:86 | J38: آية من فهرس المصحف في الشاملة غُيّرت فيها كلمة واحدة عمدًا | K38: محمد سجاد | L38: مقبول | M38: المحرّف: «نصيرا» بدل «ظهيرا»
A39: t-035 | B39: test | C39: C2 آيات محرفة اللفظ | D39: ar | E39: quran | F39: verifier | G39: منشور اليوم: ﴿وإذا أذقنا الناس رحمة فرحوا بها وإن تصبهم سيئة بما قدمت أيديهم إذا هم ييأسون﴾ — شاركها مع من تحب ولا تنس الدعاء لنا. | H39: QURAN_WORDING_DIFFERS | I39: 30:36 | J39: آية من فهرس المصحف في الشاملة غُيّرت فيها كلمة واحدة عمدًا | L39: لم يراجع | M39: المحرّف: «ييأسون» بدل «يقنطون»
A40: t-036 | B40: test | C40: C2 آيات محرفة اللفظ | D40: ar | E40: quran | F40: verifier | G40: ومن الأدلة على ذلك قوله تعالى: قُلْ مَنْ ذَا الَّذِي يَعْصِمُكُمْ مِنَ اللَّهِ إِنْ أَرَادَ بِكُمْ سُوءًا أَوْ أَرَادَ بِكُمْ رَحْمَةً وَلَا يَجِدُونَ لَهُمْ مِنْ دُونِ اللَّهِ وَلِيًّا وَلَا شَفِيعًا، وهي آية جامعة يحسن بالداعية أن يحفظها. | H40: QURAN_WORDING_DIFFERS | I40: 33:17 | J40: آية من فهرس المصحف في الشاملة غُيّرت فيها كلمة واحدة عمدًا | L40: لم يراجع | M40: المحرّف: «ولا شفيعا» بدل «ولا نصيرا»
A41: t-037 | B41: dev | C41: C2 آيات محرفة اللفظ | D41: ar | E41: quran | F41: verifier | G41: من أعظم ما يطمئن به القلب أن الله تعالى قال في كتابه: ﴿إلا رحمة منا ومتاعا إلى أجل﴾، فهذه الآية تفتح باب الأمل لكل من ضاقت به الدنيا. | H41: QURAN_WORDING_DIFFERS | I41: 36:44 | J41: آية من فهرس المصحف في الشاملة غُيّرت فيها كلمة واحدة عمدًا | K41: محمد سجاد | L41: مقبول | M41: المحرّف: «إلى أجل» بدل «إلى حين»
A42: t-038 | B42: test | C42: C2 آيات محرفة اللفظ | D42: ar | E42: quran | F42: verifier | G42: يقول الله عز وجل: أَمْ عِنْدَهُمْ خَزَائِنُ رَحْمَةِ رَبِّكَ الْكَرِيمِ الْوَهَّابِ. وفي هذا تذكير لنا بأن الرحمة أصل في تعامل المسلم مع الناس. | H42: QURAN_WORDING_DIFFERS | I42: 38:9 | J42: آية من فهرس المصحف في الشاملة غُيّرت فيها كلمة واحدة عمدًا | L42: لم يراجع | M42: المحرّف: «الكريم» بدل «العزيز»
A43: t-039 | B43: test | C43: C2 آيات محرفة اللفظ | D43: ar | E43: quran | F43: verifier | G43: أخي الكريم، تأمل قوله تعالى: «ووهبنا له أهله ومثلهم معهم رحمة منا وذكرى للعالمين»، ثم انظر كيف ينبغي أن يكون حالنا مع إخواننا في هذا المجتمع. | H43: QURAN_WORDING_DIFFERS | I43: 38:43 | J43: آية من فهرس المصحف في الشاملة غُيّرت فيها كلمة واحدة عمدًا | K43: محمد سجاد | L43: مقبول | M43: المحرّف: «للعالمين» بدل «لأولي الألباب»
A44: t-040 | B44: test | C44: C2 آيات محرفة اللفظ | D44: ar | E44: quran | F44: verifier | G44: في درس الأمس بالمركز تحدثنا عن قول الله سبحانه: ﴿وَإِذَا مَسَّ النَّاسَ ضُرٌّ دَعَوْا رَبَّهُمْ مُنِيبِينَ إِلَيْهِ ثُمَّ إِذَا أَذَاقَهُمْ مِنْهُ رَحْمَةً إِذَا فَرِيقٌ مِنْهُمْ بِرَبِّهِمْ يَكْفُرُونَ﴾، وكيف نشرح معناها لمن لا يعرف العربية. | H44: QURAN_WORDING_DIFFERS | I44: 30:33 | J44: آية من فهرس المصحف في الشاملة غُيّرت فيها كلمة واحدة عمدًا | L44: لم يراجع | M44: المحرّف: «يكفرون» بدل «يشركون»
A45: t-041 | B45: dev | C45: C2 آيات محرفة اللفظ | D45: ar | E45: quran | F45: verifier | G45: قال الله تعالى: وما كنت بجانب الطور إذ نادينا ولكن رحمة من ربك لتنذر قوما ما أتاهم من نذير من قبلك لعلهم يهتدون صدق الله العظيم. فلنجعل هذه الآية شعارنا في دعوتنا هذا الأسبوع. | H45: QURAN_WORDING_DIFFERS | I45: 28:46 | J45: آية من فهرس المصحف في الشاملة غُيّرت فيها كلمة واحدة عمدًا | K45: محمد سجاد | L45: مقبول | M45: المحرّف: «يهتدون» بدل «يتذكرون»
A46: t-042 | B46: test | C46: C2 آيات محرفة اللفظ | D46: ar | E46: quran | F46: verifier | G46: منشور اليوم: ﴿فَإِنْ أَعْرَضُوا فَمَا أَرْسَلْنَاكَ عَلَيْهِمْ حَفِيظًا إِنْ عَلَيْكَ إِلَّا الْبَلَاغُ وَإِنَّا إِذَا أَذَقْنَا الْإِنْسَانَ مِنَّا رَحْمَةً فَرِحَ بِهَا وَإِنْ تُصِبْهُمْ سَيِّئَةٌ بِمَا قَدَّمَتْ أَيْدِيهِمْ فَإِنَّ الْإِنْسَانَ ظَلُومٌ﴾ — شاركها مع من تحب ولا تنس الدعاء لنا. | H46: QURAN_WORDING_DIFFERS | I46: 42:48 | J46: آية من فهرس المصحف في الشاملة غُيّرت فيها كلمة واحدة عمدًا | L46: لم يراجع | M46: المحرّف: «ظلوم» بدل «كفور»
A47: t-043 | B47: test | C47: C2 آيات محرفة اللفظ | D47: ar | E47: quran | F47: verifier | G47: ومن الأدلة على ذلك قوله تعالى: وإذا أذقنا الناس رحمة من بعد ضراء مستهم إذا لهم مكر في آياتنا قل الله أسرع مكرا إن رسلنا يعلمون ما تمكرون، وهي آية جامعة يحسن بالداعية أن يحفظها. | H47: QURAN_WORDING_DIFFERS | I47: 10:21 | J47: آية من فهرس المصحف في الشاملة غُيّرت فيها كلمة واحدة عمدًا | L47: لم يراجع | M47: المحرّف: «يعلمون» بدل «يكتبون»
A48: t-044 | B48: test | C48: C2 آيات محرفة اللفظ | D48: ar | E48: quran | F48: verifier | G48: من أعظم ما يطمئن به القلب أن الله تعالى قال في كتابه: ﴿قَالَ يَاقَوْمِ أَرَأَيْتُمْ إِنْ كُنْتُ عَلَى بَيِّنَةٍ مِنْ رَبِّي وَآتَانِي مِنْهُ رَحْمَةً فَمَنْ يَنْصُرُنِي مِنَ اللَّهِ إِنْ عَصَيْتُهُ فَمَا تَزِيدُونَنِي غَيْرَ خَسَارٍ﴾، فهذه الآية تفتح باب الأمل لكل من ضاقت به الدنيا. | H48: QURAN_WORDING_DIFFERS | I48: 11:63 | J48: آية من فهرس المصحف في الشاملة غُيّرت فيها كلمة واحدة عمدًا | K48: محمد سجاد | L48: مقبول | M48: المحرّف: «خسار» بدل «تخسير»
A49: t-045 | B49: dev | C49: C2 آيات محرفة اللفظ | D49: ar | E49: quran | F49: verifier | G49: يقول الله عز وجل: إذ أوى الفتية إلى الكهف فقالوا ربنا آتنا من لدنك رحمة وهيئ لنا من أمرنا خيرا. وفي هذا تذكير لنا بأن الرحمة أصل في تعامل المسلم مع الناس. | H49: QURAN_WORDING_DIFFERS | I49: 18:10 | J49: آية من فهرس المصحف في الشاملة غُيّرت فيها كلمة واحدة عمدًا | K49: محمد سجاد | L49: مقبول | M49: المحرّف: «خيرا» بدل «رشدا»
A50: t-046 | B50: test | C50: C3 آيات مترجمة | D50: en | E50: quran | F50: verifier | G50: Allah says in the Quran: "And We have not sent you, [O Muhammad], except as a mercy to the worlds" Let this verse be a reminder for all of us this week. | H50: QURAN_VERIFIED | I50: 21:107 | J50: ترجمة Saheeh International من Tanzil عبر حزمة quran-json | L50: مقبول
A51: t-047 | B51: test | C51: C3 آيات مترجمة | D51: bn | E51: quran | F51: verifier | G51: আল্লাহ তাআলা কুরআনে বলেছেন: "বলুন, হে আমার বান্দাগণ যারা নিজেদের উপর যুলুম করেছ তোমরা আল্লাহর রহমত থেকে নিরাশ হয়ো না। নিশ্চয় আল্লাহ সমস্ত গোনাহ মাফ করেন। তিনি ক্ষমাশীল, পরম দয়ালু।" এই আয়াতটি আমাদের সবার জন্য একটি বড় শিক্ষা। | H51: QURAN_VERIFIED | I51: 39:53 | J51: ترجمة মুহিউদ্দীন খান من Tanzil عبر حزمة quran-json | L51: مقبول
A52: t-048 | B52: test | C52: C3 آيات مترجمة | D52: ur | E52: quran | F52: verifier | G52: اللہ تعالیٰ قرآن مجید میں فرماتا ہے: "میں نے جن اور انسانوں کو اِس کے سوا کسی کام کے لیے پیدا نہیں کیا ہے کہ وہ میری بندگی کریں" یہ آیت ہم سب کے لیے بڑی نصیحت ہے۔ | H52: QURAN_VERIFIED | I52: 51:56 | J52: ترجمة مودودی من Tanzil عبر حزمة quran-json | L52: مقبول
A53: t-049 | B53: dev | C53: C3 آيات مترجمة | D53: en | E53: quran | F53: verifier | G53: As the Quran beautifully puts it: "And when My servants ask you, [O Muhammad], concerning Me - indeed I am near. I respond to the invocation of the supplicant when he calls upon Me. So let them respond to Me [by obedience] and believe in Me that they may be [rightly] guided". Share this with a friend who needs hope today. | H53: QURAN_VERIFIED | I53: 2:186 | J53: ترجمة Saheeh International من Tanzil عبر حزمة quran-json | L53: مقبول
A54: t-050 | B54: test | C54: C3 آيات مترجمة | D54: bn | E54: quran | F54: verifier | G54: আজকের আয়াত: যারা বিশ্বাস স্থাপন করে এবং তাদের অন্তর আল্লাহর যিকির দ্বারা শান্তি লাভ করে; জেনে রাখ, আল্লাহর যিকির দ্বারাই অন্তর সমূহ শান্তি পায়। — বন্ধুদের সাথে শেয়ার করুন। | H54: QURAN_VERIFIED | I54: 13:28 | J54: ترجمة মুহিউদ্দীন খান من Tanzil عبر حزمة quran-json | L54: لم يراجع
A55: t-051 | B55: test | C55: C3 آيات مترجمة | D55: ur | E55: quran | F55: verifier | G55: آج کی آیت: لوگو، ہم نے تم کو ایک مرد اور ایک عورت سے پیدا کیا اور پھر تمہاری قومیں اور برادریاں بنا دیں تاکہ تم ایک دوسرے کو پہچانو در حقیقت اللہ کے نزدیک تم میں سب سے زیادہ عزت والا وہ ہے جو تمہارے اندر سب سے زیادہ پرہیز گار ہے یقیناً اللہ سب کچھ جاننے والا اور باخبر ہے — اسے اپنے دوستوں کے ساتھ شیئر کریں۔ | H55: QURAN_VERIFIED | I55: 49:13 | J55: ترجمة مودودی من Tanzil عبر حزمة quran-json | L55: لم يراجع
A56: t-052 | B56: test | C56: C3 آيات مترجمة | D56: en | E56: quran | F56: verifier | G56: One of my favourite verses: Invite to the way of your Lord with wisdom and good instruction, and argue with them in a way that is best. Indeed, your Lord is most knowing of who has strayed from His way, and He is most knowing of who is [rightly] guided. This is the message of Islam to humanity. | H56: QURAN_VERIFIED | I56: 16:125 | J56: ترجمة Saheeh International من Tanzil عبر حزمة quran-json | L56: لم يراجع
A57: t-053 | B57: dev | C57: C3 آيات مترجمة | D57: bn | E57: quran | F57: verifier | G57: পবিত্র কুরআনে ইরশাদ হয়েছে, "দ্বীনের ব্যাপারে কোন জবরদস্তি বা বাধ্য-বাধকতা নেই। নিঃসন্দেহে হেদায়াত গোমরাহী থেকে পৃথক হয়ে গেছে। এখন যারা গোমরাহকারী ‘তাগুত’দেরকে মানবে না এবং আল্লাহতে বিশ্বাস স্থাপন করবে, সে ধারণ করে নিয়েছে সুদৃঢ় হাতল যা ভাংবার নয়। আর আল্লাহ সবই শুনেন এবং জানেন।"। তাই আমাদের সবসময় এ কথা মনে রাখা উচিত। | H57: QURAN_VERIFIED | I57: 2:256 | J57: ترجمة মুহিউদ্দীন খান من Tanzil عبر حزمة quran-json | L57: مقبول
A58: t-054 | B58: test | C58: C3 آيات مترجمة | D58: ur | E58: quran | F58: verifier | G58: قرآن کریم میں ارشاد ہے: "کہو، وہ اللہ ہے، یکتا"۔ ہمیں ہمیشہ یہ بات یاد رکھنی چاہیے۔ | H58: QURAN_VERIFIED | I58: 112:1 | J58: ترجمة مودودی من Tanzil عبر حزمة quran-json | L58: لم يراجع
A59: t-055 | B59: test | C59: C3 آيات مترجمة | D59: en | E59: quran | F59: verifier | G59: Allah says in the Quran: "Every soul will taste death, and you will only be given your [full] compensation on the Day of Resurrection. So he who is drawn away from the Fire and admitted to Paradise has attained [his desire]. And what is the life of this world except the enjoyment of delusion" Let this verse be a reminder for all of us this week. | H59: QURAN_VERIFIED | I59: 3:185 | J59: ترجمة Saheeh International من Tanzil عبر حزمة quran-json | L59: لم يراجع
A60: t-056 | B60: test | C60: C3 آيات مترجمة | D60: bn | E60: quran | F60: verifier | G60: আল্লাহ তাআলা কুরআনে বলেছেন: "ধর্মের ব্যাপারে যারা তোমাদের বিরুদ্ধে লড়াই করেনি এবং তোমাদেরকে দেশ থেকে বহিস্কৃত করেনি, তাদের প্রতি সদাচরণ ও ইনসাফ করতে আল্লাহ তোমাদেরকে নিষেধ করেন না। নিশ্চয় আল্লাহ ইনসাফকারীদেরকে ভালবাসেন।" এই আয়াতটি আমাদের সবার জন্য একটি বড় শিক্ষা। | H60: QURAN_VERIFIED | I60: 60:8 | J60: ترجمة মুহিউদ্দীন খান من Tanzil عبر حزمة quran-json | L60: لم يراجع
A61: t-057 | B61: dev | C61: C3 آيات مترجمة | D61: ur | E61: quran | F61: verifier | G61: اللہ تعالیٰ قرآن مجید میں فرماتا ہے: "جو لوگ ہماری خاطر مجاہدہ کریں گے انہیں ہم اپنے راستے دکھائیں گے، اور یقیناً اللہ نیکو کاروں ہی کے ساتھ ہے" یہ آیت ہم سب کے لیے بڑی نصیحت ہے۔ | H61: QURAN_VERIFIED | I61: 29:69 | J61: ترجمة مودودی من Tanzil عبر حزمة quran-json | L61: مقبول
... A74: t-070 | B74: test | C74: C3 آيات مترجمة | D74: en | E74: quran | F74: verifier | G74: One of my favourite verses: Worship Allah and associate nothing with Him, and to parents do good, and to relatives, orphans, the needy, the near neighbor, the neighbor farther away, the companion at your side, the traveler, and those whom your right hands possess. Indeed, Allah does not like those who are self-deluding and boastful. This is the message of Islam to humanity. | H74: QURAN_VERIFIED | I74: 4:36 | J74: ترجمة Saheeh International من Tanzil عبر حزمة quran-json | L74: لم يراجع
A75: t-071 | B75: dev | C75: C4 أحاديث ثابتة بالعربية | D75: ar | E75: hadith | F75: verifier | G75: قال رسول الله ﷺ: «إنما الأعمال بالنيات، وإنما لكل امرئ ما نوى، فمن كانت هجرته إلى دنيا يصيبها، أو إلى امرأة ينكحها، فهجرته إلى ما هاجر إليه». فما أحوجنا اليوم إلى العمل بهذا التوجيه النبوي. | H75: HADITH_AUTHENTIC | I75: h-001 | J75: نص الحديث من الفهرس (h-001) | K75: محمد سجاد | L75: مقبول
A76: t-072 | B76: test | C76: C4 أحاديث ثابتة بالعربية | D76: ar | E76: hadith | F76: verifier | G76: عن النبي صلى الله عليه وسلم أنه قال: بني الإسلام على خمس: شهادة أن لا إله إلا الله وأن محمدا رسول الله، وإقام الصلاة، وإيتاء الزكاة، والحج، وصوم رمضان. وهذا الحديث نرسله كل جمعة في مجموعة الجالية. | H76: HADITH_AUTHENTIC | I76: h-002 | J76: نص الحديث من الفهرس (h-002) | K76: محمد سجاد | L76: مقبول
A77: t-073 | B77: test | C77: C4 أحاديث ثابتة بالعربية | D77: ar | E77: hadith | F77: verifier | G77: تذكير: يقول الحبيب المصطفى ﷺ: «الدين النصيحة. قلنا: لمن؟ قال: لله ولكتابه ولرسوله، ولأئمة المسلمين وعامتهم». اللهم اجعلنا من العاملين. | H77: HADITH_AUTHENTIC | I77: h-003 | J77: نص الحديث من الفهرس (h-003) | L77: لم يراجع
A78: t-074 | B78: test | C78: C4 أحاديث ثابتة بالعربية | D78: ar | E78: hadith | F78: verifier | G78: ومما يُستشهد به في هذا الباب قوله ﷺ: لا يؤمن أحدكم حتى يحب لأخيه ما يحب لنفسه، وقد كتبناه على لوحة المسجد. | H78: HADITH_AUTHENTIC | I78: h-005 | J78: نص الحديث من الفهرس (h-005) | L78: لم يراجع
A79: t-075 | B79: dev | C79: C4 أحاديث ثابتة بالعربية | D79: ar | E79: hadith | F79: verifier | G79: في الحديث الشريف: «المسلم من سلم المسلمون من لسانه ويده، والمهاجر من هجر ما نهى الله عنه». فليتأمل كل واحد منا هذا المعنى في بيته وعمله. | H79: HADITH_AUTHENTIC | I79: h-006 | J79: نص الحديث من الفهرس (h-006) | K79: محمد سجاد | L79: مقبول
A80: t-076 | B80: test | C80: C4 أحاديث ثابتة بالعربية | D80: ar | E80: hadith | F80: verifier | G80: رسالة اليوم من مركز الدعوة: قال ﷺ: من كان يؤمن بالله واليوم الآخر فليكرم ضيفه، ومن كان يؤمن بالله واليوم الآخر فليصل رحمه، ومن كان يؤمن بالله واليوم الآخر فليقل خيرا أو ليصمت. | H80: HADITH_AUTHENTIC | I80: h-007 | J80: نص الحديث من الفهرس (h-007) | L80: لم يراجع
A81: t-077 | B81: test | C81: C4 أحاديث ثابتة بالعربية | D81: ar | E81: hadith | F81: verifier | G81: قال رسول الله ﷺ: «إن الله كتب الإحسان على كل شيء، فإذا قتلتم فأحسنوا القتلة ، و إذا ذبحتم فأحسنوا الذبحة، و ليحد أحدكم شفرته، و ليرح ذبيحته». فما أحوجنا اليوم إلى العمل بهذا التوجيه النبوي. | H81: HADITH_AUTHENTIC | I81: h-008 | J81: نص الحديث من الفهرس (h-008) | K81: محمد سجاد | L81: مقبول
A82: t-078 | B82: test | C82: C4 أحاديث ثابتة بالعربية | D82: ar | E82: hadith | F82: verifier | G82: عن النبي صلى الله عليه وسلم أنه قال: سمعت رسول الله صلى الله عليه وسلم، وأومأ بإصبعيه إلى أذنيه: إن الحلال بين، والحرام بين، وإن بين الحلال والحرام مشبهات، لا يدري كثير من الناس أمن الحلال هي، أم من الحرام، فمن تركها؛ استبرأ لدينه وعرضه ، ومن واقعها؛ يوشك أن يواقع الحرام؛ فمن رعى إلى جنب حمى، يوشك أن يرتع فيه؛ ولكل ملك حمى، وإن حمى الله محارمه. وهذا الحديث نرسله كل جمعة في مجموعة الجالية. | H82: HADITH_AUTHENTIC | I82: h-009 | J82: نص الحديث من الفهرس (h-009) | L82: لم يراجع
A83: t-079 | B83: dev | C83: C4 أحاديث ثابتة بالعربية | D83: ar | E83: hadith | F83: verifier | G83: تذكير: يقول الحبيب المصطفى ﷺ: «دع ما يريبك إلى ما لا يريبك فإن الصدق طمأنينة والكذب ريبة». اللهم اجعلنا من العاملين. | H83: HADITH_AUTHENTIC | I83: h-010 | J83: نص الحديث من الفهرس (h-010) | K83: محمد سجاد | L83: مقبول
A84: t-080 | B84: test | C84: C4 أحاديث ثابتة بالعربية | D84: ar | E84: hadith | F84: verifier | G84: ومما يُستشهد به في هذا الباب قوله ﷺ: لا ضرر ولا ضرار، وقد كتبناه على لوحة المسجد. | H84: HADITH_AUTHENTIC | I84: h-011 | J84: نص الحديث من الفهرس (h-011) | L84: لم يراجع
A85: t-081 | B85: test | C85: C4 أحاديث ثابتة بالعربية | D85: ar | E85: hadith | F85: verifier | G85: في الحديث الشريف: «أول من بدأ بالخطبة يوم العيد قبل الصلاة مروان. فقام إليه رجل، فقال: الصلاة قبل الخطبة، فقال: قد ترك ما هنالك، فقال أبو سعيد: أما هذا فقد قضى ما عليه، سمعت رسول الله صلى الله عليه وسلم يقول: من رأى منكم منكرا فليغيره بيده، فإن لم يستطع فبلسانه، فإن لم يستطع فبقلبه، وذلك أضعف الإيمان». فليتأمل كل واحد منا هذا المعنى في بيته وعمله. | H85: HADITH_AUTHENTIC | I85: h-012 | J85: نص الحديث من الفهرس (h-012) | L85: لم يراجع
A86: t-082 | B86: test | C86: C4 أحاديث ثابتة بالعربية | D86: ar | E86: hadith | F86: verifier | G86: رسالة اليوم من مركز الدعوة: قال ﷺ: الطهور شطر الإيمان، والحمد لله تملأ الميزان. | H86: HADITH_AUTHENTIC | I86: h-013 | J86: نص الحديث من الفهرس (h-013) | K86: محمد سجاد | L86: مقبول
A87: t-083 | B87: dev | C87: C4 أحاديث ثابتة بالعربية | D87: ar | E87: hadith | F87: verifier | G87: قال رسول الله ﷺ: «أيها الناس، إن الله طيب لا يقبل إلا طيبا، وإن الله أمر المؤمنين بما أمر به المرسلين، فقال: {يا أيها الرسل كلوا من الطيبات واعملوا صالحا إني بما تعملون عليم} [المؤمنون: 51]، وقال: {يا أيها الذين آمنوا كلوا من طيبات ما رزقناكم} [البقرة: 172]، ثم ذكر الرجل يطيل السفر أشعث أغبر، يمد يديه إلى السماء، يا رب، يا رب، ومطعمه حرام، ومشربه حرام، وملبسه حرام، وغذي بالحرام، فأنى يستجاب لذلك؟!». فما أحوجنا اليوم إلى العمل بهذا التوجيه النبوي. | H87: HADITH_AUTHENTIC | I87: h-014 | J87: نص الحديث من الفهرس (h-014) | K87: محمد سجاد | L87: مقبول
A88: t-084 | B88: test | C88: C4 أحاديث ثابتة بالعربية | D88: ar | E88: hadith | F88: verifier | G88: عن النبي صلى الله عليه وسلم أنه قال: اتق الله حيثما كنت، وأتبع السيئة الحسنة تمحها، وخالق الناس بخلق حسن. وهذا الحديث نرسله كل جمعة في مجموعة الجالية. | H88: HADITH_AUTHENTIC | I88: h-015 | J88: نص الحديث من الفهرس (h-015) | L88: لم يراجع
A89: t-085 | B89: test | C89: C4 أحاديث ثابتة بالعربية | D89: ar | E89: hadith | F89: verifier | G89: تذكير: يقول الحبيب المصطفى ﷺ: «احفظ الله يحفظك، احفظ الله تجده تجاهك ، إذا سألت فاسأل الله، وإذا استعنت فاستعن بالله». اللهم اجعلنا من العاملين. | H89: HADITH_AUTHENTIC | I89: h-016 | J89: نص الحديث من الفهرس (h-016) | L89: لم يراجع
A90: t-086 | B90: test | C90: C4 أحاديث ثابتة بالعربية | D90: ar | E90: hadith | F90: verifier | G90: ومما يُستشهد به في هذا الباب قوله ﷺ: آخر ما أدرك الناس من كلام النبوة الأولى، إذا لم تستح، فاصنع ما شئت، وقد كتبناه على لوحة المسجد. | H90: HADITH_AUTHENTIC | I90: h-017 | J90: نص الحديث من الفهرس (h-017) | L90: لم يراجع
A91: t-087 | B91: dev | C91: C4 أحاديث ثابتة بالعربية | D91: ar | E91: hadith | F91: verifier | G91: في الحديث الشريف: «قلت: يا رسول الله، قل لي في الإسلام قولا لا أسأل عنه أحدا بعدك، وفي حديث أبي أسامة: غيرك، قال: قل: آمنت بالله، ثم استقم». فليتأمل كل واحد منا هذا المعنى في بيته وعمله. | H91: HADITH_AUTHENTIC | I91: h-018 | J91: نص الحديث من الفهرس (h-018) | K91: محمد سجاد | L91: مقبول
A92: t-088 | B92: test | C92: C4 أحاديث ثابتة بالعربية | D92: ar | E92: hadith | F92: verifier | G92: رسالة اليوم من مركز الدعوة: قال ﷺ: الإيمان بضع وسبعون شعبة، والحياء شعبة من الإيمان. | H92: HADITH_AUTHENTIC | I92: h-019 | J92: نص الحديث من الفهرس (h-019) | K92: محمد سجاد | L92: مقبول
A93: t-089 | B93: test | C93: C4 أحاديث ثابتة بالعربية | D93: ar | E93: hadith | F93: verifier | G93: قال رسول الله ﷺ: «الحياء لا يأتي إلا بخير. فقال بشير بن كعب: إنه مكتوب في الحكمة: أن منه وقارا، ومنه سكينة، فقال عمران: أحدثك عن رسول الله صلى الله عليه وسلم، وتحدثني عن صحفك؟!». فما أحوجنا اليوم إلى العمل بهذا التوجيه النبوي. | H93: HADITH_AUTHENTIC | I93: h-020 | J93: نص الحديث من الفهرس (h-020) | L93: لم يراجع
A94: t-090 | B94: test | C94: C4 أحاديث ثابتة بالعربية | D94: ar | E94: hadith | F94: verifier | G94: عن النبي صلى الله عليه وسلم أنه قال: كلمتان خفيفتان على اللسان، ثقيلتان في الميزان، حبيبتان إلى الرحمن: سبحان الله العظيم، سبحان الله وبحمده. وهذا الحديث نرسله كل جمعة في مجموعة الجالية. | H94: HADITH_AUTHENTIC | I94: h-021 | J94: نص الحديث من الفهرس (h-021) | L94: لم يراجع
A95: t-091 | B95: dev | C95: C4 أحاديث ثابتة بالعربية | D95: ar | E95: hadith | F95: verifier | G95: تذكير: يقول الحبيب المصطفى ﷺ: «من قال: سبحان الله وبحمده، في يوم مائة مرة، حطت خطاياه وإن كانت مثل زبد البحر». اللهم اجعلنا من العاملين. | H95: HADITH_AUTHENTIC | I95: h-022 | J95: نص الحديث من الفهرس (h-022) | K95: محمد سجاد | L95: مقبول
A96: t-092 | B96: test | C96: C4 أحاديث ثابتة بالعربية | D96: ar | E96: hadith | F96: verifier | G96: ومما يُستشهد به في هذا الباب قوله ﷺ: الكلمة الطيبة صدقة، وكل خطوة يخطوها إلى الصلاة صدقة، وقد كتبناه على لوحة المسجد. | H96: HADITH_AUTHENTIC | I96: h-023 | J96: نص الحديث من الفهرس (h-023) | L96: لم يراجع
A97: t-093 | B97: test | C97: C4 أحاديث ثابتة بالعربية | D97: ar | E97: hadith | F97: verifier | G97: في الحديث الشريف: «خيركم من تعلم القرآن وعلمه. قال: وأقرأ أبو عبد الرحمن في إمرة عثمان، حتى كان الحجاج قال: وذاك الذي أقعدني مقعدي هذا». فليتأمل كل واحد منا هذا المعنى في بيته وعمله. | H97: HADITH_AUTHENTIC | I97: h-025 | J97: نص الحديث من الفهرس (h-025) | L97: لم يراجع
A98: t-094 | B98: test | C98: C4 أحاديث ثابتة بالعربية | D98: ar | E98: hadith | F98: verifier | G98: رسالة اليوم من مركز الدعوة: قال ﷺ: من سلك طريقا يلتمس فيه علما، سهل الله له طريقا إلى الجنة. | H98: HADITH_AUTHENTIC | I98: h-026 | J98: نص الحديث من الفهرس (h-026) | K98: محمد سجاد | L98: مقبول
A99: t-095 | B99: test | C99: C4 أحاديث ثابتة بالعربية | D99: ar | E99: hadith | F99: verifier | G99: قال رسول الله ﷺ: «إذا مات ابن آدم انقطع عمله إلا من ثلاث : صدقة جارية , أو علم ينتفع به, أو ولد صالح يدعو له». فما أحوجنا اليوم إلى العمل بهذا التوجيه النبوي. | H99: HADITH_AUTHENTIC | I99: h-028 | J99: نص الحديث من الفهرس (h-028) | L99: لم يراجع
A100: t-096 | B100: dev | C100: C5 أحاديث ثابتة مترجمة | D100: en | E100: hadith | F100: verifier | G100: The Prophet Muhammad (peace be upon him) said: "If you have no shame, do as you wish". What a beautiful reminder for our community. | H100: HADITH_AUTHENTIC | I100: h-017 | J100: الصيغة المتداولة من الفهرس (h-017) | K100: محمد سجاد | L100: مقبول
A101: t-097 | B101: test | C101: C5 أحاديث ثابتة مترجمة | D101: bn | E101: hadith | F101: verifier | G101: প্রিয় নবী (সা.)-এর বাণী: বলো, আমি আল্লাহর প্রতি ঈমান আনলাম, অতঃপর অবিচল থাকো। এই হাদিসটি আপনার পরিবারের সাথে শেয়ার করুন। | H101: HADITH_AUTHENTIC | I101: h-018 | J101: الصيغة المتداولة من الفهرس (h-018) | K101: محمد سجاد | L101: مقبول
A102: t-098 | B102: test | C102: C5 أحاديث ثابتة مترجمة | D102: ur | E102: hadith | F102: verifier | G102: آج کی حدیث: "ایمان کی ستر سے زائد شاخیں ہیں" — (الحدیث) | H102: HADITH_AUTHENTIC | I102: h-019 | J102: الصيغة المتداولة من الفهرس (h-019) | K102: محمد سجاد | L102: مقبول
A103: t-099 | B103: test | C103: C5 أحاديث ثابتة مترجمة | D103: en | E103: hadith | F103: verifier | G103: The Prophet Muhammad (peace be upon him) said: "Modesty brings nothing but good". What a beautiful reminder for our community. | H103: HADITH_AUTHENTIC | I103: h-020 | J103: الصيغة المتداولة من الفهرس (h-020) | K103: محمد سجاد | L103: مقبول
A104: t-100 | B104: dev | C104: C5 أحاديث ثابتة مترجمة | D104: bn | E104: hadith | F104: verifier | G104: প্রিয় নবী (সা.)-এর বাণী: দুটি বাক্য জিহ্বায় হালকা, মিযানে ভারী: সুবহানাল্লাহি ওয়া বিহামদিহী, সুবহানাল্লাহিল আযীম। এই হাদিসটি আপনার পরিবারের সাথে শেয়ার করুন। | H104: HADITH_AUTHENTIC | I104: h-021 | J104: الصيغة المتداولة من الفهرس (h-021) | K104: محمد سجاد | L104: مقبول
A105: t-101 | B105: test | C105: C5 أحاديث ثابتة مترجمة | D105: ur | E105: hadith | F105: verifier | G105: آج کی حدیث: "جو دن میں سو مرتبہ سبحان اللہ وبحمدہ کہے اس کے گناہ سمندر کے جھاگ کے برابر ہوں تب بھی معاف کر دیے جاتے ہیں" — (الحدیث) | H105: HADITH_AUTHENTIC | I105: h-022 | J105: الصيغة المتداولة من الفهرس (h-022) | L105: لم يراجع
A106: t-102 | B106: test | C106: C5 أحاديث ثابتة مترجمة | D106: en | E106: hadith | F106: verifier | G106: The Prophet Muhammad (peace be upon him) said: "A good word is charity". What a beautiful reminder for our community. | H106: HADITH_AUTHENTIC | I106: h-023 | J106: الصيغة المتداولة من الفهرس (h-023) | L106: لم يراجع
A107: t-103 | B107: test | C107: C5 أحاديث ثابتة مترجمة | D107: bn | E107: hadith | F107: verifier | G107: প্রিয় নবী (সা.)-এর বাণী: তোমাদের মধ্যে সর্বোত্তম সেই যে কুরআন শেখে এবং শেখায়। এই হাদিসটি আপনার পরিবারের সাথে শেয়ার করুন। | H107: HADITH_AUTHENTIC | I107: h-025 | J107: الصيغة المتداولة من الفهرس (h-025) | L107: لم يراجع
A108: t-104 | B108: dev | C108: C5 أحاديث ثابتة مترجمة | D108: ur | E108: hadith | F108: verifier | G108: آج کی حدیث: "جو علم کی تلاش میں راستہ چلے اللہ اس کے لیے جنت کا راستہ آسان کر دیتا ہے" — (الحدیث) | H108: HADITH_AUTHENTIC | I108: h-026 | J108: الصيغة المتداولة من الفهرس (h-026) | K108: محمد سجاد | L108: مقبول
A109: t-105 | B109: test | C109: C5 أحاديث ثابتة مترجمة | D109: en | E109: hadith | F109: verifier | G109: The Prophet Muhammad (peace be upon him) said: "When a person dies his deeds end except three: ongoing charity, beneficial knowledge, a righteous child who prays for him". What a beautiful reminder for our community. | H109: HADITH_AUTHENTIC | I109: h-028 | J109: الصيغة المتداولة من الفهرس (h-028) | L109: لم يراجع
A110: t-106 | B110: test | C110: C5 أحاديث ثابتة مترجمة | D110: bn | E110: hadith | F110: verifier | G110: প্রিয় নবী (সা.)-এর বাণী: দুনিয়া মুমিনের জন্য কারাগার এবং কাফিরের জন্য জান্নাত। এই হাদিসটি আপনার পরিবারের সাথে শেয়ার করুন। | H110: HADITH_AUTHENTIC | I110: h-030 | J110: الصيغة المتداولة من الفهرس (h-030) | L110: لم يراجع
A111: t-107 | B111: test | C111: C5 أحاديث ثابتة مترجمة | D111: ur | E111: hadith | F111: verifier | G111: آج کی حدیث: "دنیا میں ایسے رہو جیسے تم اجنبی یا مسافر ہو" — (الحدیث) | H111: HADITH_AUTHENTIC | I111: h-031 | J111: الصيغة المتداولة من الفهرس (h-031) | L111: لم يراجع
A112: t-108 | B112: dev | C112: C5 أحاديث ثابتة مترجمة | D112: en | E112: hadith | F112: verifier | G112: The Prophet Muhammad (peace be upon him) said: "If the world were worth the wing of a mosquito to Allah, He would not give a disbeliever a sip of water from it". What a beautiful reminder for our community. | H112: HADITH_AUTHENTIC | I112: h-033 | J112: الصيغة المتداولة من الفهرس (h-033) | K112: محمد سجاد | L112: مقبول
...

Sheet التقدّم
A1: الفئة | B1: المستهدف | C1: المُدخل | D1: منها dev | E1: منها مقبول | F1: المتبقي | G1: الحالة المتوقعة غالبًا
A2: C1 آيات عربية صحيحة | B2: 25 | C2: =COUNTIFS(الحالات!$C$5:$C$204,A2,الحالات!$G$5:$G$204,"<>") -> 25 | D2: =COUNTIFS(الحالات!$C$5:$C$204,A2,الحالات!$G$5:$G$204,"<>",الحالات!$B$5:$B$204,"dev") -> 6 | E2: =COUNTIFS(الحالات!$C$5:$C$204,A2,الحالات!$G$5:$G$204,"<>",الحالات!$L$5:$L$204,"مقبول") -> 17 | F2: =MAX(0,B2-C2) -> 0 | G2: QURAN_VERIFIED
A3: C2 آيات محرفة اللفظ | B3: 20 | C3: =COUNTIFS(الحالات!$C$5:$C$204,A3,الحالات!$G$5:$G$204,"<>") -> 20 | D3: =COUNTIFS(الحالات!$C$5:$C$204,A3,الحالات!$G$5:$G$204,"<>",الحالات!$B$5:$B$204,"dev") -> 5 | E3: =COUNTIFS(الحالات!$C$5:$C$204,A3,الحالات!$G$5:$G$204,"<>",الحالات!$L$5:$L$204,"مقبول") -> 10 | F3: =MAX(0,B3-C3) -> 0 | G3: QURAN_WORDING_DIFFERS
A4: C3 آيات مترجمة | B4: 25 | C4: =COUNTIFS(الحالات!$C$5:$C$204,A4,الحالات!$G$5:$G$204,"<>") -> 25 | D4: =COUNTIFS(الحالات!$C$5:$C$204,A4,الحالات!$G$5:$G$204,"<>",الحالات!$B$5:$B$204,"dev") -> 6 | E4: =COUNTIFS(الحالات!$C$5:$C$204,A4,الحالات!$G$5:$G$204,"<>",الحالات!$L$5:$L$204,"مقبول") -> 12 | F4: =MAX(0,B4-C4) -> 0 | G4: QURAN_VERIFIED
A5: C4 أحاديث ثابتة بالعربية | B5: 25 | C5: =COUNTIFS(الحالات!$C$5:$C$204,A5,الحالات!$G$5:$G$204,"<>") -> 25 | D5: =COUNTIFS(الحالات!$C$5:$C$204,A5,الحالات!$G$5:$G$204,"<>",الحالات!$B$5:$B$204,"dev") -> 6 | E5: =COUNTIFS(الحالات!$C$5:$C$204,A5,الحالات!$G$5:$G$204,"<>",الحالات!$L$5:$L$204,"مقبول") -> 11 | F5: =MAX(0,B5-C5) -> 0 | G5: HADITH_AUTHENTIC
A6: C5 أحاديث ثابتة مترجمة | B6: 25 | C6: =COUNTIFS(الحالات!$C$5:$C$204,A6,الحالات!$G$5:$G$204,"<>") -> 25 | D6: =COUNTIFS(الحالات!$C$5:$C$204,A6,الحالات!$G$5:$G$204,"<>",الحالات!$B$5:$B$204,"dev") -> 6 | E6: =COUNTIFS(الحالات!$C$5:$C$204,A6,الحالات!$G$5:$G$204,"<>",الحالات!$L$5:$L$204,"مقبول") -> 12 | F6: =MAX(0,B6-C6) -> 0 | G6: HADITH_AUTHENTIC
A7: C6 أحاديث ضعيفة | B7: 14 | C7: =COUNTIFS(الحالات!$C$5:$C$204,A7,الحالات!$G$5:$G$204,"<>") -> 14 | D7: =COUNTIFS(الحالات!$C$5:$C$204,A7,الحالات!$G$5:$G$204,"<>",الحالات!$B$5:$B$204,"dev") -> 4 | E7: =COUNTIFS(الحالات!$C$5:$C$204,A7,الحالات!$G$5:$G$204,"<>",الحالات!$L$5:$L$204,"مقبول") -> 9 | F7: =MAX(0,B7-C7) -> 0 | G7: HADITH_WEAK
A8: C7 أحاديث موضوعة | B8: 13 | C8: =COUNTIFS(الحالات!$C$5:$C$204,A8,الحالات!$G$5:$G$204,"<>") -> 13 | D8: =COUNTIFS(الحالات!$C$5:$C$204,A8,الحالات!$G$5:$G$204,"<>",الحالات!$B$5:$B$204,"dev") -> 4 | E8: =COUNTIFS(الحالات!$C$5:$C$204,A8,الحالات!$G$5:$G$204,"<>",الحالات!$L$5:$L$204,"مقبول") -> 9 | F8: =MAX(0,B8-C8) -> 0 | G8: HADITH_FABRICATED
A9: C8 أقوال منسوبة لا أصل لها في الفهرس | B9: 38 | C9: =COUNTIFS(الحالات!$C$5:$C$204,A9,الحالات!$G$5:$G$204,"<>") -> 38 | D9: =COUNTIFS(الحالات!$C$5:$C$204,A9,الحالات!$G$5:$G$204,"<>",الحالات!$B$5:$B$204,"dev") -> 10 | E9: =COUNTIFS(الحالات!$C$5:$C$204,A9,الحالات!$G$5:$G$204,"<>",الحالات!$L$5:$L$204,"مقبول") -> 17 | F9: =MAX(0,B9-C9) -> 0 | G9: NOT_FOUND
A10: C9 حالات حرجة من الحزمة | B10: 15 | C10: =COUNTIFS(الحالات!$C$5:$C$204,A10,الحالات!$G$5:$G$204,"<>") -> 15 | D10: =COUNTIFS(الحالات!$C$5:$C$204,A10,الحالات!$G$5:$G$204,"<>",الحالات!$B$5:$B$204,"dev") -> 3 | E10: =COUNTIFS(الحالات!$C$5:$C$204,A10,الحالات!$G$5:$G$204,"<>",الحالات!$L$5:$L$204,"مقبول") -> 9 | F10: =MAX(0,B10-C10) -> 0 | G10: REFER_TO_SCHOLAR
A11: المجموع | B11: =SUM(B2:B10) -> 200 | C11: =SUM(C2:C10) -> 200 | D11: =SUM(D2:D10) -> 50 | E11: =SUM(E2:E10) -> 106 | F11: =SUM(F2:F10) -> 0
A13: الأعمدة C–F تُحسب تلقائيًا من ورقة «الحالات»؛ لا تكتب فيها. الأمثلة الرمادية (EX) غير محسوبة لأنها خارج النطاق.
